pyplayready/__init__.py
pyplayready/cdm.py
pyplayready/crypto/__init__.py
pyplayready/crypto/ecc_key.py
pyplayready/crypto/elgamal.py
pyplayready/crypto/key_wrap.py
pyplayready/device/__init__.py
pyplayready/device/structs.py
pyplayready/license/key.py
pyplayready/license/license.py
pyplayready/license/xml_key.py
pyplayready/license/xmrlicense.py
pyplayready/main.py
pyplayready/misc/drmresults.py
pyplayready/misc/exceptions.py
pyplayready/misc/revocation_list.py
pyplayready/misc/soap_message.py
pyplayready/misc/storage.py
pyplayready/remote/remotecdm.py
pyplayready/remote/serve.py
pyplayready/system/bcert.py
pyplayready/system/builder.py
pyplayready/system/pssh.py
pyplayready/system/session.py
pyplayready/system/util.py
pyplayready/system/wrmheader.py
pyplayready-0.8.2.dist-info/entry_points.txt
pyplayready-0.8.2.dist-info/licenses/LICENSE
pyplayready-0.8.2.dist-info/METADATA
pyplayready-0.8.2.dist-info/WHEEL
pyplayready-0.8.2.dist-info/RECORD
