Metadata-Version: 2.4
Name: pyplayready
Version: 0.8.2
Summary: pyplayready CDM (Content Decryption Module) implementation in Python.
License: CC BY-NC-ND 4.0
License-File: LICENSE
Keywords: python,drm,playready,microsoft
Author: DevLARLEY, Erevoc
Requires-Python: >=3.8,<4.0
Classifier: Development Status :: 5 - Production/Stable
Classifier: Intended Audience :: Developers
Classifier: Intended Audience :: End Users/Desktop
Classifier: License :: Other/Proprietary License
Classifier: Natural Language :: English
Classifier: Operating System :: OS Independent
Classifier: Programming Language :: Python :: 3
Classifier: Programming Language :: Python :: 3.8
Classifier: Programming Language :: Python :: 3.9
Classifier: Programming Language :: Python :: 3.10
Classifier: Programming Language :: Python :: 3.11
Classifier: Programming Language :: Python :: 3.12
Classifier: Programming Language :: Python :: 3.13
Classifier: Programming Language :: Python :: 3.14
Classifier: Topic :: Multimedia :: Video
Classifier: Topic :: Security :: Cryptography
Classifier: Topic :: Software Development :: Libraries :: Python Modules
Requires-Dist: ECPy (>=1.2.5,<2.0.0)
Requires-Dist: PyYAML (>=6.0.1,<7.0.0)
Requires-Dist: aiohttp (>=3.9.1,<4.0.0)
Requires-Dist: click (>=8.1.7,<9.0.0)
Requires-Dist: construct (==2.8.8)
Requires-Dist: cryptography (>=45.0.6,<46.0.0)
Requires-Dist: platformdirs (>=4.4.0,<5.0.0)
Requires-Dist: pycryptodome (>=3.21.0,<4.0.0)
Requires-Dist: requests (>=2.32.3,<3.0.0)
Project-URL: Issues, https://git.gay/ready-dl/pyplayready/issues
Project-URL: Repository, https://git.gay/ready-dl/pyplayready
